<?xml version="1.0" encoding="ISO-8859-1"?>
<!DOCTYPE table_mapping PUBLIC "-//W3C//DTD XHTML 1.0 Strict//EN" "http://www.w3.org/TR/xhtml1/DTD/xhtml1-strict.dtd">
<table_mapping lang="en" xml:lang="en" xmlns="http://www.w3.org/1999/xhtml">
  <agregado>
    <idagregado>
      <name>idagregado</name>
      <type>int4</type>
      <len>4</len>
      <flags>not_null default_nextval%28agregado_idagregado_seq%29 primary_key</flags>
    </idagregado>
    <idpessoa>
      <name>idpessoa</name>
      <type>int4</type>
      <len>4</len>
      <flags>not_null</flags>
    </idpessoa>
    <nome>
      <name>nome</name>
      <type>varchar</type>
      <len>-1</len>
      <flags>not_null</flags>
    </nome>
    <cnpjcpf>
      <name>cnpjcpf</name>
      <type>varchar</type>
      <len>-1</len>
      <flags />
    </cnpjcpf>
    <inscestadualrg>
      <name>inscestadualrg</name>
      <type>varchar</type>
      <len>-1</len>
      <flags />
    </inscestadualrg>
    <datacadastro>
      <name>datacadastro</name>
      <type>timestamp</type>
      <len>8</len>
      <flags>not_null</flags>
    </datacadastro>
    <databaixa>
      <name>databaixa</name>
      <type>timestamp</type>
      <len>8</len>
      <flags />
    </databaixa>
    <situacao>
      <name>situacao</name>
      <type>bool</type>
      <len>1</len>
      <flags />
    </situacao>
  </agregado>
  <baixaconhecimento>
    <idbaixaconhecimento>
      <name>idbaixaconhecimento</name>
      <type>int4</type>
      <len>4</len>
      <flags>not_null default_nextval%28baixaconhecimento_idbaixaconhecimento_seq%29 primary_key</flags>
    </idbaixaconhecimento>
    <idconhecimento>
      <name>idconhecimento</name>
      <type>int4</type>
      <len>4</len>
      <flags>not_null</flags>
    </idconhecimento>
    <nome>
      <name>nome</name>
      <type>varchar</type>
      <len>-1</len>
      <flags>not_null</flags>
    </nome>
    <data>
      <name>data</name>
      <type>date</type>
      <len>4</len>
      <flags>not_null</flags>
    </data>
    <hora>
      <name>hora</name>
      <type>time</type>
      <len>8</len>
      <flags>not_null</flags>
    </hora>
    <datacadastro>
      <name>datacadastro</name>
      <type>timestamp</type>
      <len>8</len>
      <flags>not_null</flags>
    </datacadastro>
    <databaixa>
      <name>databaixa</name>
      <type>timestamp</type>
      <len>8</len>
      <flags />
    </databaixa>
    <situacao>
      <name>situacao</name>
      <type>bool</type>
      <len>1</len>
      <flags>not_null</flags>
    </situacao>
  </baixaconhecimento>
  <categoria>
    <idcategoria>
      <name>idcategoria</name>
      <type>int4</type>
      <len>4</len>
      <flags>not_null default_nextval%28categoria_idcategoria_seq%29 primary_key</flags>
    </idcategoria>
    <descricao>
      <name>descricao</name>
      <type>varchar</type>
      <len>-1</len>
      <flags>not_null</flags>
    </descricao>
    <datacadastro>
      <name>datacadastro</name>
      <type>timestamp</type>
      <len>8</len>
      <flags>not_null</flags>
    </datacadastro>
    <databaixa>
      <name>databaixa</name>
      <type>timestamp</type>
      <len>8</len>
      <flags />
    </databaixa>
    <situacao>
      <name>situacao</name>
      <type>bool</type>
      <len>1</len>
      <flags>not_null</flags>
    </situacao>
  </categoria>
  <cliente>
    <idcliente>
      <name>idcliente</name>
      <type>int4</type>
      <len>4</len>
      <flags>not_null default_nextval%28cliente_idcliente_seq%29 primary_key</flags>
    </idcliente>
    <idpessoa>
      <name>idpessoa</name>
      <type>int4</type>
      <len>4</len>
      <flags>not_null</flags>
    </idpessoa>
    <idfrequenciacoleta>
      <name>idfrequenciacoleta</name>
      <type>int4</type>
      <len>4</len>
      <flags />
    </idfrequenciacoleta>
    <nome>
      <name>nome</name>
      <type>varchar</type>
      <len>-1</len>
      <flags>not_null</flags>
    </nome>
    <cnpjcpf>
      <name>cnpjcpf</name>
      <type>varchar</type>
      <len>-1</len>
      <flags>not_null</flags>
    </cnpjcpf>
    <inscestadualrg>
      <name>inscestadualrg</name>
      <type>varchar</type>
      <len>-1</len>
      <flags />
    </inscestadualrg>
    <datacadastro>
      <name>datacadastro</name>
      <type>timestamp</type>
      <len>8</len>
      <flags>not_null</flags>
    </datacadastro>
    <databaixa>
      <name>databaixa</name>
      <type>timestamp</type>
      <len>8</len>
      <flags />
    </databaixa>
    <situacao>
      <name>situacao</name>
      <type>bool</type>
      <len>1</len>
      <flags>not_null</flags>
    </situacao>
  </cliente>
  <coleta>
    <idcoleta>
      <name>idcoleta</name>
      <type>int4</type>
      <len>4</len>
      <flags>not_null default_nextval%28coleta_idcoleta_seq%29 primary_key multiple_key</flags>
    </idcoleta>
    <versao>
      <name>versao</name>
      <type>int4</type>
      <len>4</len>
      <flags>not_null primary_key multiple_key</flags>
    </versao>
    <codigo>
      <name>codigo</name>
      <type>varchar</type>
      <len>-1</len>
      <flags>not_null</flags>
    </codigo>
    <idcliente>
      <name>idcliente</name>
      <type>int4</type>
      <len>4</len>
      <flags />
    </idcliente>
    <idcontato>
      <name>idcontato</name>
      <type>int4</type>
      <len>4</len>
      <flags />
    </idcontato>
    <idveiculo>
      <name>idveiculo</name>
      <type>int4</type>
      <len>4</len>
      <flags />
    </idveiculo>
    <idfornecedor>
      <name>idfornecedor</name>
      <type>int4</type>
      <len>4</len>
      <flags />
    </idfornecedor>
    <idusuario>
      <name>idusuario</name>
      <type>int4</type>
      <len>4</len>
      <flags />
    </idusuario>
    <idusuariobaixa>
      <name>idusuariobaixa</name>
      <type>int4</type>
      <len>4</len>
      <flags />
    </idusuariobaixa>
    <idstatus>
      <name>idstatus</name>
      <type>int4</type>
      <len>4</len>
      <flags />
    </idstatus>
    <idmotivo>
      <name>idmotivo</name>
      <type>int4</type>
      <len>4</len>
      <flags />
    </idmotivo>
    <idembalagem>
      <name>idembalagem</name>
      <type>int4</type>
      <len>4</len>
      <flags />
    </idembalagem>
    <idrestricao>
      <name>idrestricao</name>
      <type>int4</type>
      <len>4</len>
      <flags />
    </idrestricao>
    <data>
      <name>data</name>
      <type>date</type>
      <len>4</len>
      <flags>not_null</flags>
    </data>
    <hora>
      <name>hora</name>
      <type>time</type>
      <len>8</len>
      <flags>not_null</flags>
    </hora>
    <qtdadenotafiscal>
      <name>qtdadenotafiscal</name>
      <type>int4</type>
      <len>4</len>
      <flags />
    </qtdadenotafiscal>
    <qtdadevolumes>
      <name>qtdadevolumes</name>
      <type>int4</type>
      <len>4</len>
      <flags />
    </qtdadevolumes>
    <peso>
      <name>peso</name>
      <type>float8</type>
      <len>8</len>
      <flags />
    </peso>
    <obscoleta>
      <name>obscoleta</name>
      <type>text</type>
      <len>-1</len>
      <flags />
    </obscoleta>
    <datacadastro>
      <name>datacadastro</name>
      <type>timestamp</type>
      <len>8</len>
      <flags>not_null</flags>
    </datacadastro>
    <databaixa>
      <name>databaixa</name>
      <type>timestamp</type>
      <len>8</len>
      <flags />
    </databaixa>
  </coleta>
  <conhecimento>
    <idconhecimento>
      <name>idconhecimento</name>
      <type>int4</type>
      <len>4</len>
      <flags>not_null default_nextval%28conhecimento_idconhecimento_seq%29 primary_key</flags>
    </idconhecimento>
    <idmanifesto>
      <name>idmanifesto</name>
      <type>int4</type>
      <len>4</len>
      <flags>not_null</flags>
    </idmanifesto>
    <numero>
      <name>numero</name>
      <type>varchar</type>
      <len>-1</len>
      <flags>not_null</flags>
    </numero>
    <dataemissao>
      <name>dataemissao</name>
      <type>date</type>
      <len>4</len>
      <flags>not_null</flags>
    </dataemissao>
    <idstatusconhecimento>
      <name>idstatusconhecimento</name>
      <type>int4</type>
      <len>4</len>
      <flags />
    </idstatusconhecimento>
    <idclienteremetente>
      <name>idclienteremetente</name>
      <type>int4</type>
      <len>4</len>
      <flags>not_null</flags>
    </idclienteremetente>
    <idclientedestinatario>
      <name>idclientedestinatario</name>
      <type>int4</type>
      <len>4</len>
      <flags>not_null</flags>
    </idclientedestinatario>
    <peso>
      <name>peso</name>
      <type>float8</type>
      <len>8</len>
      <flags>not_null</flags>
    </peso>
    <volumes>
      <name>volumes</name>
      <type>int4</type>
      <len>4</len>
      <flags>not_null</flags>
    </volumes>
    <valornotafiscal>
      <name>valornotafiscal</name>
      <type>float8</type>
      <len>8</len>
      <flags>not_null</flags>
    </valornotafiscal>
    <valorfrete>
      <name>valorfrete</name>
      <type>float8</type>
      <len>8</len>
      <flags>not_null</flags>
    </valorfrete>
    <datacadastro>
      <name>datacadastro</name>
      <type>timestamp</type>
      <len>8</len>
      <flags>not_null</flags>
    </datacadastro>
    <databaixa>
      <name>databaixa</name>
      <type>timestamp</type>
      <len>8</len>
      <flags />
    </databaixa>
    <situacao>
      <name>situacao</name>
      <type>bool</type>
      <len>1</len>
      <flags />
    </situacao>
  </conhecimento>
  <contato>
    <idcontato>
      <name>idcontato</name>
      <type>int4</type>
      <len>4</len>
      <flags>not_null default_nextval%28contato_idcontato_seq%29 primary_key</flags>
    </idcontato>
    <idpessoa>
      <name>idpessoa</name>
      <type>int4</type>
      <len>4</len>
      <flags>not_null</flags>
    </idpessoa>
    <nome>
      <name>nome</name>
      <type>varchar</type>
      <len>-1</len>
      <flags>not_null</flags>
    </nome>
    <funcao>
      <name>funcao</name>
      <type>varchar</type>
      <len>-1</len>
      <flags />
    </funcao>
    <telefone>
      <name>telefone</name>
      <type>bpchar</type>
      <len>-1</len>
      <flags>not_null</flags>
    </telefone>
    <celular>
      <name>celular</name>
      <type>bpchar</type>
      <len>-1</len>
      <flags />
    </celular>
    <ramal>
      <name>ramal</name>
      <type>varchar</type>
      <len>-1</len>
      <flags />
    </ramal>
    <email>
      <name>email</name>
      <type>varchar</type>
      <len>-1</len>
      <flags />
    </email>
    <login>
      <name>login</name>
      <type>varchar</type>
      <len>-1</len>
      <flags />
    </login>
    <senha>
      <name>senha</name>
      <type>varchar</type>
      <len>-1</len>
      <flags />
    </senha>
    <datacadastro>
      <name>datacadastro</name>
      <type>timestamp</type>
      <len>8</len>
      <flags>not_null</flags>
    </datacadastro>
    <databaixa>
      <name>databaixa</name>
      <type>timestamp</type>
      <len>8</len>
      <flags />
    </databaixa>
    <situacao>
      <name>situacao</name>
      <type>bool</type>
      <len>1</len>
      <flags>not_null</flags>
    </situacao>
  </contato>
  <embalagem>
    <idembalagem>
      <name>idembalagem</name>
      <type>int4</type>
      <len>4</len>
      <flags>not_null default_nextval%28embalagem_idembalagem_seq%29 primary_key</flags>
    </idembalagem>
    <descricao>
      <name>descricao</name>
      <type>varchar</type>
      <len>-1</len>
      <flags>not_null</flags>
    </descricao>
    <datacadastro>
      <name>datacadastro</name>
      <type>timestamp</type>
      <len>8</len>
      <flags>not_null</flags>
    </datacadastro>
    <databaixa>
      <name>databaixa</name>
      <type>timestamp</type>
      <len>8</len>
      <flags />
    </databaixa>
    <situacao>
      <name>situacao</name>
      <type>bool</type>
      <len>1</len>
      <flags>not_null</flags>
    </situacao>
  </embalagem>
  <entregas>
    <idsaidamanifesto>
      <name>idsaidamanifesto</name>
      <type>int4</type>
      <len>4</len>
      <flags>not_null primary_key multiple_key</flags>
    </idsaidamanifesto>
    <idconhecimento>
      <name>idconhecimento</name>
      <type>int4</type>
      <len>4</len>
      <flags>not_null primary_key multiple_key</flags>
    </idconhecimento>
    <datacadastro>
      <name>datacadastro</name>
      <type>timestamp</type>
      <len>8</len>
      <flags>not_null</flags>
    </datacadastro>
    <databaixa>
      <name>databaixa</name>
      <type>timestamp</type>
      <len>8</len>
      <flags />
    </databaixa>
    <situacao>
      <name>situacao</name>
      <type>bool</type>
      <len>1</len>
      <flags>not_null</flags>
    </situacao>
  </entregas>
  <fornecedor>
    <idfornecedor>
      <name>idfornecedor</name>
      <type>int4</type>
      <len>4</len>
      <flags>not_null default_nextval%28fornecedor_idfornecedor_seq%29 primary_key</flags>
    </idfornecedor>
    <idpessoa>
      <name>idpessoa</name>
      <type>int4</type>
      <len>4</len>
      <flags>not_null</flags>
    </idpessoa>
    <inscestadual>
      <name>inscestadual</name>
      <type>varchar</type>
      <len>-1</len>
      <flags>not_null</flags>
    </inscestadual>
    <cnpj>
      <name>cnpj</name>
      <type>varchar</type>
      <len>-1</len>
      <flags>not_null</flags>
    </cnpj>
    <nomefantasia>
      <name>nomefantasia</name>
      <type>varchar</type>
      <len>-1</len>
      <flags>not_null</flags>
    </nomefantasia>
    <razaosocial>
      <name>razaosocial</name>
      <type>varchar</type>
      <len>-1</len>
      <flags>not_null</flags>
    </razaosocial>
    <datacadastro>
      <name>datacadastro</name>
      <type>timestamp</type>
      <len>8</len>
      <flags>not_null</flags>
    </datacadastro>
    <databaixa>
      <name>databaixa</name>
      <type>timestamp</type>
      <len>8</len>
      <flags />
    </databaixa>
    <situacao>
      <name>situacao</name>
      <type>bool</type>
      <len>1</len>
      <flags>not_null</flags>
    </situacao>
  </fornecedor>
  <frequenciacoleta>
    <idfrequenciacoleta>
      <name>idfrequenciacoleta</name>
      <type>int4</type>
      <len>4</len>
      <flags>not_null default_nextval%28frequenciacoleta_idfrequenciacoleta_seq%29 primary_key</flags>
    </idfrequenciacoleta>
    <descricao>
      <name>descricao</name>
      <type>varchar</type>
      <len>-1</len>
      <flags>not_null</flags>
    </descricao>
    <qtdadedias>
      <name>qtdadedias</name>
      <type>int4</type>
      <len>4</len>
      <flags>not_null</flags>
    </qtdadedias>
    <datacadastro>
      <name>datacadastro</name>
      <type>timestamp</type>
      <len>8</len>
      <flags>not_null</flags>
    </datacadastro>
    <databaixa>
      <name>databaixa</name>
      <type>timestamp</type>
      <len>8</len>
      <flags />
    </databaixa>
    <situacao>
      <name>situacao</name>
      <type>bool</type>
      <len>1</len>
      <flags>not_null</flags>
    </situacao>
  </frequenciacoleta>
  <manifesto>
    <idmanifesto>
      <name>idmanifesto</name>
      <type>int4</type>
      <len>4</len>
      <flags>not_null default_nextval%28manifesto_idmanifesto_seq%29 primary_key</flags>
    </idmanifesto>
    <cidade>
      <name>cidade</name>
      <type>varchar</type>
      <len>-1</len>
      <flags>not_null</flags>
    </cidade>
    <idfornecedor>
      <name>idfornecedor</name>
      <type>int4</type>
      <len>4</len>
      <flags>not_null</flags>
    </idfornecedor>
    <idstatusmanifesto>
      <name>idstatusmanifesto</name>
      <type>int4</type>
      <len>4</len>
      <flags />
    </idstatusmanifesto>
    <codigo>
      <name>codigo</name>
      <type>varchar</type>
      <len>-1</len>
      <flags />
    </codigo>
    <numero>
      <name>numero</name>
      <type>varchar</type>
      <len>-1</len>
      <flags>not_null</flags>
    </numero>
    <horariochegada>
      <name>horariochegada</name>
      <type>time</type>
      <len>8</len>
      <flags>not_null</flags>
    </horariochegada>
    <totalctrc>
      <name>totalctrc</name>
      <type>float8</type>
      <len>8</len>
      <flags>not_null</flags>
    </totalctrc>
    <totalvolumes>
      <name>totalvolumes</name>
      <type>int4</type>
      <len>4</len>
      <flags>not_null</flags>
    </totalvolumes>
    <totalpeso>
      <name>totalpeso</name>
      <type>float8</type>
      <len>8</len>
      <flags>not_null</flags>
    </totalpeso>
    <valortotalnotafiscal>
      <name>valortotalnotafiscal</name>
      <type>float8</type>
      <len>8</len>
      <flags>not_null</flags>
    </valortotalnotafiscal>
    <valortotalfrete>
      <name>valortotalfrete</name>
      <type>float8</type>
      <len>8</len>
      <flags>not_null</flags>
    </valortotalfrete>
    <datacadastro>
      <name>datacadastro</name>
      <type>timestamp</type>
      <len>8</len>
      <flags />
    </datacadastro>
    <databaixa>
      <name>databaixa</name>
      <type>timestamp</type>
      <len>8</len>
      <flags />
    </databaixa>
    <situacao>
      <name>situacao</name>
      <type>bool</type>
      <len>1</len>
      <flags />
    </situacao>
  </manifesto>
  <motivo>
    <idmotivo>
      <name>idmotivo</name>
      <type>int4</type>
      <len>4</len>
      <flags>not_null default_nextval%28motivo_idmotivo_seq%29 primary_key</flags>
    </idmotivo>
    <descricao>
      <name>descricao</name>
      <type>varchar</type>
      <len>-1</len>
      <flags>not_null</flags>
    </descricao>
    <datacadastro>
      <name>datacadastro</name>
      <type>timestamp</type>
      <len>8</len>
      <flags>not_null</flags>
    </datacadastro>
    <databaixa>
      <name>databaixa</name>
      <type>timestamp</type>
      <len>8</len>
      <flags />
    </databaixa>
    <situacao>
      <name>situacao</name>
      <type>bool</type>
      <len>1</len>
      <flags>not_null</flags>
    </situacao>
  </motivo>
  <nivel>
    <idnivel>
      <name>idnivel</name>
      <type>int4</type>
      <len>4</len>
      <flags>not_null default_nextval%28nivel_idnivel_seq%29 primary_key</flags>
    </idnivel>
    <descricao>
      <name>descricao</name>
      <type>varchar</type>
      <len>-1</len>
      <flags>not_null</flags>
    </descricao>
    <datacadastro>
      <name>datacadastro</name>
      <type>timestamp</type>
      <len>8</len>
      <flags>not_null</flags>
    </datacadastro>
    <databaixa>
      <name>databaixa</name>
      <type>timestamp</type>
      <len>8</len>
      <flags />
    </databaixa>
    <situacao>
      <name>situacao</name>
      <type>bool</type>
      <len>1</len>
      <flags>not_null</flags>
    </situacao>
  </nivel>
  <pessoa>
    <idpessoa>
      <name>idpessoa</name>
      <type>int4</type>
      <len>4</len>
      <flags>not_null default_nextval%28pessoa_idpessoa_seq%29 primary_key</flags>
    </idpessoa>
    <rua>
      <name>rua</name>
      <type>varchar</type>
      <len>-1</len>
      <flags />
    </rua>
    <numero>
      <name>numero</name>
      <type>int4</type>
      <len>4</len>
      <flags />
    </numero>
    <complemento>
      <name>complemento</name>
      <type>varchar</type>
      <len>-1</len>
      <flags />
    </complemento>
    <bairro>
      <name>bairro</name>
      <type>varchar</type>
      <len>-1</len>
      <flags />
    </bairro>
    <cep>
      <name>cep</name>
      <type>bpchar</type>
      <len>-1</len>
      <flags />
    </cep>
    <cidade>
      <name>cidade</name>
      <type>varchar</type>
      <len>-1</len>
      <flags />
    </cidade>
    <estado>
      <name>estado</name>
      <type>bpchar</type>
      <len>-1</len>
      <flags />
    </estado>
    <telefone>
      <name>telefone</name>
      <type>bpchar</type>
      <len>-1</len>
      <flags />
    </telefone>
    <fax>
      <name>fax</name>
      <type>bpchar</type>
      <len>-1</len>
      <flags />
    </fax>
    <email>
      <name>email</name>
      <type>varchar</type>
      <len>-1</len>
      <flags />
    </email>
  </pessoa>
  <restricao>
    <idrestricao>
      <name>idrestricao</name>
      <type>int4</type>
      <len>4</len>
      <flags>not_null default_nextval%28restricao_idrestricao_seq%29 primary_key</flags>
    </idrestricao>
    <descricao>
      <name>descricao</name>
      <type>varchar</type>
      <len>-1</len>
      <flags>not_null</flags>
    </descricao>
    <datacadastro>
      <name>datacadastro</name>
      <type>timestamp</type>
      <len>8</len>
      <flags>not_null</flags>
    </datacadastro>
    <databaixa>
      <name>databaixa</name>
      <type>timestamp</type>
      <len>8</len>
      <flags />
    </databaixa>
    <situacao>
      <name>situacao</name>
      <type>bool</type>
      <len>1</len>
      <flags>not_null</flags>
    </situacao>
  </restricao>
  <saidamanifesto>
    <idsaidamanifesto>
      <name>idsaidamanifesto</name>
      <type>int4</type>
      <len>4</len>
      <flags>not_null default_nextval%28saidamanifesto_idsaidamanifesto_seq%29 primary_key</flags>
    </idsaidamanifesto>
    <idveiculo>
      <name>idveiculo</name>
      <type>int4</type>
      <len>4</len>
      <flags>not_null</flags>
    </idveiculo>
    <data>
      <name>data</name>
      <type>date</type>
      <len>4</len>
      <flags>not_null</flags>
    </data>
    <hora>
      <name>hora</name>
      <type>time</type>
      <len>8</len>
      <flags>not_null</flags>
    </hora>
    <datacadastro>
      <name>datacadastro</name>
      <type>timestamp</type>
      <len>8</len>
      <flags>not_null</flags>
    </datacadastro>
    <databaixa>
      <name>databaixa</name>
      <type>timestamp</type>
      <len>8</len>
      <flags />
    </databaixa>
    <situacao>
      <name>situacao</name>
      <type>bool</type>
      <len>1</len>
      <flags>not_null</flags>
    </situacao>
  </saidamanifesto>
  <status>
    <idstatus>
      <name>idstatus</name>
      <type>int4</type>
      <len>4</len>
      <flags>not_null default_nextval%28status_idstatus_seq%29 primary_key</flags>
    </idstatus>
    <descricao>
      <name>descricao</name>
      <type>varchar</type>
      <len>-1</len>
      <flags>not_null</flags>
    </descricao>
    <datacadastro>
      <name>datacadastro</name>
      <type>timestamp</type>
      <len>8</len>
      <flags>not_null</flags>
    </datacadastro>
    <databaixa>
      <name>databaixa</name>
      <type>timestamp</type>
      <len>8</len>
      <flags />
    </databaixa>
    <situacao>
      <name>situacao</name>
      <type>bool</type>
      <len>1</len>
      <flags>not_null</flags>
    </situacao>
  </status>
  <statusconhecimento>
    <idstatusconhecimento>
      <name>idstatusconhecimento</name>
      <type>int4</type>
      <len>4</len>
      <flags>not_null default_nextval%28statusconhecimento_idstatusconhecimento_seq%29 primary_key</flags>
    </idstatusconhecimento>
    <descricao>
      <name>descricao</name>
      <type>varchar</type>
      <len>-1</len>
      <flags>not_null</flags>
    </descricao>
    <datacadastro>
      <name>datacadastro</name>
      <type>timestamp</type>
      <len>8</len>
      <flags>not_null</flags>
    </datacadastro>
    <databaixa>
      <name>databaixa</name>
      <type>timestamp</type>
      <len>8</len>
      <flags />
    </databaixa>
    <situacao>
      <name>situacao</name>
      <type>bool</type>
      <len>1</len>
      <flags>not_null</flags>
    </situacao>
  </statusconhecimento>
  <statusmanifesto>
    <idstatusmanifesto>
      <name>idstatusmanifesto</name>
      <type>int4</type>
      <len>4</len>
      <flags>not_null default_nextval%28statusmanifesto_idstatusmanifesto_seq%29 primary_key</flags>
    </idstatusmanifesto>
    <descricao>
      <name>descricao</name>
      <type>varchar</type>
      <len>-1</len>
      <flags />
    </descricao>
    <datacadastro>
      <name>datacadastro</name>
      <type>timestamp</type>
      <len>8</len>
      <flags />
    </datacadastro>
    <databaixa>
      <name>databaixa</name>
      <type>timestamp</type>
      <len>8</len>
      <flags />
    </databaixa>
    <situacao>
      <name>situacao</name>
      <type>bool</type>
      <len>1</len>
      <flags />
    </situacao>
  </statusmanifesto>
  <usuario>
    <idusuario>
      <name>idusuario</name>
      <type>int4</type>
      <len>4</len>
      <flags>not_null default_nextval%28usuario_idusuario_seq%29 primary_key</flags>
    </idusuario>
    <idnivel>
      <name>idnivel</name>
      <type>int4</type>
      <len>4</len>
      <flags>not_null</flags>
    </idnivel>
    <nome>
      <name>nome</name>
      <type>varchar</type>
      <len>-1</len>
      <flags>not_null</flags>
    </nome>
    <login>
      <name>login</name>
      <type>varchar</type>
      <len>-1</len>
      <flags>not_null</flags>
    </login>
    <senha>
      <name>senha</name>
      <type>varchar</type>
      <len>-1</len>
      <flags>not_null</flags>
    </senha>
    <datacadastro>
      <name>datacadastro</name>
      <type>timestamp</type>
      <len>8</len>
      <flags>not_null</flags>
    </datacadastro>
    <databaixa>
      <name>databaixa</name>
      <type>timestamp</type>
      <len>8</len>
      <flags />
    </databaixa>
    <situacao>
      <name>situacao</name>
      <type>bool</type>
      <len>1</len>
      <flags>not_null</flags>
    </situacao>
  </usuario>
  <veiculo>
    <idveiculo>
      <name>idveiculo</name>
      <type>int4</type>
      <len>4</len>
      <flags>not_null default_nextval%28veiculo_idveiculo_seq%29 primary_key</flags>
    </idveiculo>
    <idcategoria>
      <name>idcategoria</name>
      <type>int4</type>
      <len>4</len>
      <flags>not_null</flags>
    </idcategoria>
    <idagregado>
      <name>idagregado</name>
      <type>int4</type>
      <len>4</len>
      <flags>not_null</flags>
    </idagregado>
    <placa>
      <name>placa</name>
      <type>bpchar</type>
      <len>-1</len>
      <flags />
    </placa>
    <marca>
      <name>marca</name>
      <type>varchar</type>
      <len>-1</len>
      <flags />
    </marca>
    <modelo>
      <name>modelo</name>
      <type>varchar</type>
      <len>-1</len>
      <flags />
    </modelo>
    <prefixo>
      <name>prefixo</name>
      <type>varchar</type>
      <len>-1</len>
      <flags>not_null</flags>
    </prefixo>
    <datacadastro>
      <name>datacadastro</name>
      <type>timestamp</type>
      <len>8</len>
      <flags>not_null</flags>
    </datacadastro>
    <databaixa>
      <name>databaixa</name>
      <type>timestamp</type>
      <len>8</len>
      <flags />
    </databaixa>
    <situacao>
      <name>situacao</name>
      <type>bool</type>
      <len>1</len>
      <flags>not_null</flags>
    </situacao>
  </veiculo>
</table_mapping>